{"inkVersion":20,"root":[[{"#":"theme: dark"},{"#":"author: Hadrien Debris"},{"->":"DEATH"},["done",{"#f":5,"#n":"g-0"}],null],"done",{"DEATH":[["^This morning, opening your eyes seems easier than usual, as if your eyelids were lighter. However, your head feels fuzzy. You probably overslept, needing some time to recollect your spirits but at least you are feeling refreshed.","\n","^You rapidly understand that you are not home anymore.","\n","^You keep blinking as the landscape before you does not seem to stop changing.","\n","^A tall figure stands beside you seemingly oblivious to the large fire a few feet away.","\n","^\"ARE YOU OK?\"","\n","ev","str","^Nod","/str","/ev",{"*":".^.c-0","flg":20},["ev",{"^->":"DEATH.0.16.$r1"},{"temp=":"$r"},"str",{"->":".^.s"},[{"#n":"$r1"}],"/str","/ev",{"*":".^.^.c-1","flg":18},{"s":["^\"Probably...\"",{"->":"$r","var":true},null]}],["ev",{"^->":"DEATH.0.17.$r1"},{"temp=":"$r"},"str",{"->":".^.s"},[{"#n":"$r1"}],"/str","/ev",{"*":".^.^.c-2","flg":18},{"s":["^\"I'm not so sure.\"",{"->":"$r","var":true},null]}],{"c-0":["\n","^You acknowledge faintly.","\n",{"->":".^.^.g-0"},{"#f":5}],"c-1":["ev",{"^->":"DEATH.0.c-1.$r2"},"/ev",{"temp=":"$r"},{"->":".^.^.16.s"},[{"#n":"$r2"}],"\n","^The silhouette gives you time to gather your thoughts.","\n",{"->":".^.^.g-0"},{"#f":5}],"c-2":["ev",{"^->":"DEATH.0.c-2.$r2"},"/ev",{"temp=":"$r"},{"->":".^.^.17.s"},[{"#n":"$r2"}],"\n","^The silhouette seems to understand your situation.","\n",{"->":".^.^.g-0"},{"#f":5}],"g-0":["^\"WHAT IS THE LAST THING YOU REMEMBER?\"","\n","^Staring at the fire, you begin to remember a few things. ",{"->":"memory"},"\n",{"#f":5}]}],{"#f":1}],"memory":[[["ev",{"^->":"memory.0.0.$r1"},{"temp=":"$r"},"str",{"->":".^.s"},[{"#n":"$r1"}],"/str","/ev",{"*":".^.^.c-0","flg":18},{"s":["^\"There was a fire.\"",{"->":"$r","var":true},null]}],["ev",{"^->":"memory.0.1.$r1"},{"temp=":"$r"},"str",{"->":".^.s"},[{"#n":"$r1"}],"/str","/ev",{"*":".^.^.c-1","flg":18},{"s":["^\"There were... children?\"",{"->":"$r","var":true},null]}],["ev",{"^->":"memory.0.2.$r1"},{"temp=":"$r"},"str",{"->":".^.s"},[{"#n":"$r1"}],"/str","/ev",{"*":".^.^.c-2","flg":18},{"s":["^\"There was something falling from the sky!\"",{"->":"$r","var":true},null]}],"ev",{"CNT?":".^.c-1"},{"CNT?":".^.c-2"},"&&","/ev",{"*":".^.c-3","flg":25},{"c-0":["ev",{"^->":"memory.0.c-0.$r2"},"/ev",{"temp=":"$r"},{"->":".^.^.0.s"},[{"#n":"$r2"}],"\n","^I THINK I CAN SEE WHERE *THAT'S* COMING FROM. ",{"->":"memory"},"\n",{"#f":5}],"c-1":["ev",{"^->":"memory.0.c-1.$r2"},"/ev",{"temp=":"$r"},{"->":".^.^.1.s"},[{"#n":"$r2"}],"\n","^WHAT ABOUT THEM?","\n",[["ev",{"^->":"memory.0.c-1.9.0.$r1"},{"temp=":"$r"},"str",{"->":".^.s"},[{"#n":"$r1"}],"/str","/ev",{"*":".^.^.c-0","flg":18},{"s":["^\"Are they safe?\" ",{"->":"$r","var":true},null]}],["ev",{"^->":"memory.0.c-1.9.1.$r1"},{"temp=":"$r"},"str",{"->":".^.s"},[{"#n":"$r1"}],"/str","/ev",{"*":".^.^.c-1","flg":18},{"s":["^\"They were in danger.\" ",{"->":"$r","var":true},null]}],["ev",{"^->":"memory.0.c-1.9.2.$r1"},{"temp=":"$r"},"str",{"->":".^.s"},[{"#n":"$r1"}],"/str","/ev",{"*":".^.^.c-2","flg":18},{"s":["^\"I hurt them.\" ",{"->":"$r","var":true},null]}],{"c-0":["ev",{"^->":"memory.0.c-1.9.c-0.$r2"},"/ev",{"temp=":"$r"},{"->":".^.^.0.s"},[{"#n":"$r2"}],"\n","^WELL, THEY ARE NOW. ",{"->":"memory"},"\n",{"#f":5}],"c-1":["ev",{"^->":"memory.0.c-1.9.c-1.$r2"},"/ev",{"temp=":"$r"},{"->":".^.^.1.s"},[{"#n":"$r2"}],"\n","^NOT ANYMORE. ",{"->":"memory"},"\n",{"#f":5}],"c-2":["ev",{"^->":"memory.0.c-1.9.c-2.$r2"},"/ev",{"temp=":"$r"},{"->":".^.^.2.s"},[{"#n":"$r2"}],{"->":"memory_failed"},"\n",{"#f":5}]}],{"#f":5}],"c-2":["ev",{"^->":"memory.0.c-2.$r2"},"/ev",{"temp=":"$r"},{"->":".^.^.2.s"},[{"#n":"$r2"}],"\n","^WHAT WAS IT?","\n",[["ev",{"^->":"memory.0.c-2.9.0.$r1"},{"temp=":"$r"},"str",{"->":".^.s"},[{"#n":"$r1"}],"/str","/ev",{"*":".^.^.c-0","flg":18},{"s":["^\"A giant ball of fire.\"",{"->":"$r","var":true},null]}],["ev",{"^->":"memory.0.c-2.9.1.$r1"},{"temp=":"$r"},"str",{"->":".^.s"},[{"#n":"$r1"}],"/str","/ev",{"*":".^.^.c-1","flg":18},{"s":["^\"The Moon!\"",{"->":"$r","var":true},null]}],["ev",{"^->":"memory.0.c-2.9.2.$r1"},{"temp=":"$r"},"str",{"->":".^.s"},[{"#n":"$r1"}],"/str","/ev",{"*":".^.^.c-2","flg":18},{"s":["^\"It looked like... People screaming?\"",{"->":"$r","var":true},null]}],{"c-0":["ev",{"^->":"memory.0.c-2.9.c-0.$r2"},"/ev",{"temp=":"$r"},{"->":".^.^.0.s"},[{"#n":"$r2"}],"\n","^CLOSE ENOUGH. ",{"->":"memory"},"\n",{"#f":5}],"c-1":["ev",{"^->":"memory.0.c-2.9.c-1.$r2"},"/ev",{"temp=":"$r"},{"->":".^.^.1.s"},[{"#n":"$r2"}],"\n","^AREN'T YOU A BIT OVER DRAMATIC? ",{"->":"memory"},"\n",{"#f":5}],"c-2":["ev",{"^->":"memory.0.c-2.9.c-2.$r2"},"/ev",{"temp=":"$r"},{"->":".^.^.2.s"},[{"#n":"$r2"}],"\n","^INDEED. ",{"->":"memory"},"\n",{"#f":5}]}],{"#f":5}],"c-3":["\n","^LET ME SUM UP.","\n",{"->":"to_be_continued"},{"->":"memory"},{"#f":5}]}],{"#f":1}],"saved":["^(saved) YES. YOU SAVED THEM. ",{"->":"memory"},"\n",{"#f":1}],"hurt":["^(hurt) YOU'RE RIGHT. ",{"->":"memory_failed"},"\n",{"#f":1}],"memory_failed":["^The silhouette points a bonely finger at a boat floating on what seemed to be a gravity-defying river.","\n","^\"GET IN.\"","\n","^The boat starts taking speed and it all fades...","\n","^TO RED. ","end","\n",{"#f":1}],"to_be_continued":["^To be continued... ","end","\n","end",{"#f":1}],"#f":1}],"listDefs":{}}